[
	{
		"name": "Witcher",
		"unitType": "Sword",
		"uniqueTo": "Witchers",
		"replaces": "Longswordsman",
		"movement": 4,
		"strength": 50,
		"cost": 500,
		"requiredTech": "Steel",
		"attackSound": "metalhit"
	},
	{
		"name": "Sorcerer",
		"unitType": "Ranged",
		"uniqueTo": "Witchers",
		"replaces": "Great Prophet",
		"movement": 4,
		"strength": 1,
		"rangedStrength": 25,
		"attackSound": "metalhit"
	},
	{
		"name": "Temerian Infantry",
		"unitType": "Sword",
		"uniqueTo": "Temeria",
		"replaces": "Longswordsman",
		"movement": 2,
		"strength": 15,
		"cost": 60,
		"requiredTech": "Steel",
		"attackSound": "metalhit"
	},
	{
		"name": "Lyrian Arbalest",
		"unitType": "Archery",
		"uniqueTo": "Temeria",
		"replaces": "Crossbowman",
		"movement": 2,
		"strength": 10,
		"rangedStrength":20,
		"cost": 70,
		"requiredTech": "Machinery",
		"attackSound": "metalhit"
	},
	{
		"name": "Iorveth's archers",
		"unitType": "Archery",
		"uniqueTo": "Mahakam",
		"replaces": "Crossbowman",
		"movement": 2,
		"strength": 10,
		"rangedStrength":25,
		"cost": 200,
		"requiredTech": "Machinery",
		"attackSound": "metalhit"
	},
	{
		"name": "Dwarf",
		"unitType": "Sword",
		"uniqueTo": "Mahakam",
		"replaces": "Longswordsman",
		"movement": 1,
		"strength": 35,
		"cost": 150,
		"requiredTech": "Steel",
		"attackSound": "metalhit"
	},
]
